markdown_anki_decks/__init__.py
markdown_anki_decks/cli.py
markdown_anki_decks/styles/markdown.css
markdown_anki_decks/styles/pygments-dark.css
markdown_anki_decks/styles/pygments.css
markdown_anki_decks/sync.py
markdown_anki_decks/utils.py
markdown_anki_decks-1.1.1.dist-info/entry_points.txt
markdown_anki_decks-1.1.1.dist-info/LICENSE.txt
markdown_anki_decks-1.1.1.dist-info/WHEEL
markdown_anki_decks-1.1.1.dist-info/METADATA
markdown_anki_decks-1.1.1.dist-info/RECORD
