Metadata-Version: 2.1
Name: markdown-anki-decks
Version: 1.1.1
Summary: A command line program to convert markdown files into anki decks.
Home-page: https://github.com/lukesmurray/markdown-anki-decks
License: MIT
Author: Luke Murray
Author-email: lukepigeonmail@gmail.com
Requires-Python: >=3.7.0,<4.0.0
Classifier: Development Status :: 5 - Production/Stable
Classifier: Environment :: Console
Classifier: License :: OSI Approved :: MIT License
Classifier: Programming Language :: Python :: 3
Classifier: Programming Language :: Python :: 3.10
Classifier: Programming Language :: Python :: 3.7
Classifier: Programming Language :: Python :: 3.8
Classifier: Programming Language :: Python :: 3.9
Classifier: Topic :: Education
Classifier: Topic :: Text Processing :: Markup :: Markdown
Requires-Dist: Markdown (>=3.3.6,<4.0.0)
Requires-Dist: beautifulsoup4 (>=4.10.0,<5.0.0)
Requires-Dist: colorama (>=0.4.4,<0.5.0)
Requires-Dist: genanki (>=0.13.0,<0.14.0)
Requires-Dist: python-frontmatter (>=1.0.0,<2.0.0)
Requires-Dist: shellingham (>=1.4.0,<2.0.0)
Requires-Dist: typer (>=0.4.0,<0.5.0)
Project-URL: Repository, https://github.com/lukesmurray/markdown-anki-decks
